sceala/__init__.py
sceala/sceala.py
sceala-0.0.1.dist-info/licenses/LICENCE
sceala-0.0.1.dist-info/METADATA
sceala-0.0.1.dist-info/WHEEL
sceala-0.0.1.dist-info/top_level.txt
sceala-0.0.1.dist-info/RECORD
