Metadata-Version: 2.4
Name: sceala
Version: 0.0.1
Summary: Complement for nuacht which pulls stories from the entries in the database.
Author-email: Riain Ó Tuathail <rotuathail01@gmail.com>
License-Expression: MIT
Classifier: Programming Language :: Python :: 3
Classifier: Operating System :: OS Independent
Requires-Python: >=3.9
License-File: LICENCE
Requires-Dist: beautifulsoup4==4.14.3
Requires-Dist: requests==2.32.5
Requires-Dist: tldextract==5.3.0
Dynamic: license-file
